gradio_navbar/__init__.py
gradio_navbar/navbar.py
gradio_navbar/navbar.pyi
gradio_navbar/templates/component/index.js
gradio_navbar/templates/component/style.css
gradio_navbar/templates/example/index.js
gradio_navbar/templates/example/style.css
gradio_navbar-0.0.1.dist-info/METADATA
gradio_navbar-0.0.1.dist-info/WHEEL
gradio_navbar-0.0.1.dist-info/RECORD
