Metadata-Version: 2.3
Name: gradio_navbar
Version: 0.0.1
Summary: Gradio custom navbar component
Project-URL: repository, https://github.com/DigitalKin-ai/gradio_navbar
Author-email: Thibaud Perrin <t.perrin@digitalkin.ai>
License: Apache-2.0
Keywords: UI-component,gradio,gradio-custom-component,gradio-navbar,navar-component,navbar
Classifier: Development Status :: 3 - Alpha
Classifier: Operating System :: OS Independent
Classifier: Programming Language :: Python :: 3
Classifier: Programming Language :: Python :: 3 :: Only
Classifier: Programming Language :: Python :: 3.8
Classifier: Programming Language :: Python :: 3.9
Classifier: Programming Language :: Python :: 3.10
Classifier: Programming Language :: Python :: 3.11
Classifier: Topic :: Scientific/Engineering
Classifier: Topic :: Scientific/Engineering :: Artificial Intelligence
Classifier: Topic :: Scientific/Engineering :: Visualization
Requires-Python: >=3.10
Requires-Dist: gradio<6.0,>=4.0
Provides-Extra: dev
Requires-Dist: build; extra == 'dev'
Requires-Dist: twine; extra == 'dev'
